reqompyler/__init__.py
reqompyler/cli.py
reqompyler/reqompyler.py
reqompyler-0.1.0.dist-info/AUTHORS.md
reqompyler-0.1.0.dist-info/LICENSE
reqompyler-0.1.0.dist-info/METADATA
reqompyler-0.1.0.dist-info/WHEEL
reqompyler-0.1.0.dist-info/entry_points.txt
reqompyler-0.1.0.dist-info/top_level.txt
reqompyler-0.1.0.dist-info/RECORD
