Metadata-Version: 2.1
Name: reqompyler
Version: 0.1.0
Summary: Use pip-tools to compile a requirements.in folder into pinned dependencies.
Home-page: https://github.com/zurutech/reqompyler
Author: Zuru Tech HK Limited, All rights reserved.
Author-email: ml@zuru.tech
License: Apache License, Version 2.0
Keywords: reqompyler,pip-tools,dependencies
Platform: UNKNOWN
Classifier: Development Status :: 2 - Pre-Alpha
Classifier: Intended Audience :: Developers
Classifier: License :: OSI Approved :: Apache Software License
Classifier: Natural Language :: English
Classifier: Programming Language :: Python :: 3.7
Classifier: Programming Language :: Python :: 3.8
Classifier: Topic :: System :: Systems Administration
Requires-Python: >=3.7
Requires-Dist: Click (>=7.0)
Requires-Dist: pip-tools (>=4.4.1)
